Workbook

Sheet Start Here
B2: PRICING BY THE SERVING
B3: Turn a pan of food into a per-person price you can trust
B5: THE PROBLEM
B6: Customers ask "how much for a pan?" — so that's how you've priced. But a "pan" isn't a fixed amount. How full you pack it, how deep the dish is, and what's in it all change how many people it actually feeds. When you divide a pan price by a number of servings you guessed by eye, you never really know your cost or your profit per plate.
B8: THE FIX: PORTION BY WEIGHT
B9: Weight is the one honest unit. It works the same for jollof rice, lasagna, greens, mac & cheese — anything. Do it once per dish and you'll never guess again. All you need is a $15 kitchen scale.
B11: 1 Weigh the EMPTY pan.
B12: Write down the number (in ounces).
B13: 2 Weigh the FULL pan.
B14: Same scale, dish packed the way you'd sell it.
B15: 3 Food weight = Full − Empty.
B16: The scale did the honest counting for you.
... B35: Shaded cells = you type here. White cells = the workbook fills them in.

Sheet Serving Size Guide
B2: SERVING SIZE GUIDE
B3: Typical portion weights. These are starting points — set YOUR own number per dish and write it down once.
B5: Dish type | C5: Serving size (oz) | D5: Notes
B6: Protein — main course | C6: 6 – 8 | D6: Bone-in cuts run heavier. This is the star of the plate.
B7: Protein — buffet / multiple dishes | C7: 4 – 5 | D7: People take less when there's variety on the table.
B8: Rice / starch — as the anchor | C8: 6 – 8 | D8: e.g. jollof where rice is the main event.
B9: Rice / starch — as a side | C9: 4 – 6 | D9: About ¾–1 cup cooked.
B10: Casserole (lasagna) — main | C10: 8 – 10 | D10: Roughly 1/8 to 1/10 of a 9×13 pan.
B11: Casserole — side / buffet | C11: 5 – 6 | D11: Smaller cut alongside other mains.
B12: Vegetables / sides | C12: 3 – 4 | D12: Greens, beans, roasted veg.
B13: Stew / soup (with a starch) | C13: 8 – 10 | D13: By weight in the bowl, starch served separately.
B15: Handy conversions: 1 lb = 16 oz • 1 cup cooked rice ≈ 6–7 oz • scoop sizes drift, so weigh instead
B17: Tip: match the serving size to how the food is being served. A plated dinner where your dish is the main gets the larger number; a buffet with 5 other options gets the smaller one.

Sheet Pan Pricing Calculator
B2: PAN PRICING CALCULATOR
B3: Fill the shaded cells. White columns calculate automatically. Two examples are filled in — type over them or add your own rows below.
C4: WEIGH THE PAN | H4: YOUR COSTS | M4: SET YOUR PRICE
B5: Dish | C5: Empty pan (oz) | D5: Full pan (oz) | E5: Food wt (oz) | F5: Serving (oz) | G5: Servings | H5: Ingredients ($) | I5: Labor ($) | J5: Packaging ($) | K5: Total cost ($) | L5: Cost / serving | M5: Margin % | N5: Price / serving | O5: Price / pan
B6: EXAMPLES — for learning only (these do NOT appear in the Quote Builder dropdown)
B7: Jollof Chicken & Rice | C7: 90 | D7: 330 | E7: =IF(OR(C7="",D7=""),"",D7-C7) -> 240 | F7: 7 | G7: =IF(OR(E7="",F7="",F7=0),"",E7/F7) -> 34.285714 | H7: 34 | I7: 18 | J7: 6 | K7: =IF(COUNT(H7:J7)=0,"",SUM(H7:J7)) -> 58 | L7: =IF(OR(G7="",G7=0,K7=""),"",K7/G7) -> 1.6916667 | M7: 0.4 | N7: =IF(OR(L7="",M7="",M7>=1),"",L7/(1-M7)) -> 2.8194444 | O7: =IF(OR(N7="",G7=""),"",N7*G7) -> 96.666667
B8: Beef Lasagna (9×13) | C8: 80 | D8: 260 | E8: =IF(OR(C8="",D8=""),"",D8-C8) -> 180 | F8: 9 | G8: =IF(OR(E8="",F8="",F8=0),"",E8/F8) -> 20 | H8: 22 | I8: 15 | J8: 5 | K8: =IF(COUNT(H8:J8)=0,"",SUM(H8:J8)) -> 42 | L8: =IF(OR(G8="",G8=0,K8=""),"",K8/G8) -> 2.1 | M8: 0.45 | N8: =IF(OR(L8="",M8="",M8>=1),"",L8/(1-M8)) -> 3.8181818 | O8: =IF(OR(N8="",G8=""),"",N8*G8) -> 76.363636
B9: YOUR DISHES — enter your real dishes here (these fill the Quote Builder dropdown)
E10: =IF(OR(C10="",D10=""),"",D10-C10) | G10: =IF(OR(E10="",F10="",F10=0),"",E10/F10) | K10: =IF(COUNT(H10:J10)=0,"",SUM(H10:J10)) | L10: =IF(OR(G10="",G10=0,K10=""),"",K10/G10) | N10: =IF(OR(L10="",M10="",M10>=1),"",L10/(1-M10)) | O10: =IF(OR(N10="",G10=""),"",N10*G10)
E11: =IF(OR(C11="",D11=""),"",D11-C11) | G11: =IF(OR(E11="",F11="",F11=0),"",E11/F11) | K11: =IF(COUNT(H11:J11)=0,"",SUM(H11:J11)) | L11: =IF(OR(G11="",G11=0,K11=""),"",K11/G11) | N11: =IF(OR(L11="",M11="",M11>=1),"",L11/(1-M11)) | O11: =IF(OR(N11="",G11=""),"",N11*G11)
E12: =IF(OR(C12="",D12=""),"",D12-C12) | G12: =IF(OR(E12="",F12="",F12=0),"",E12/F12) | K12: =IF(COUNT(H12:J12)=0,"",SUM(H12:J12)) | L12: =IF(OR(G12="",G12=0,K12=""),"",K12/G12) | N12: =IF(OR(L12="",M12="",M12>=1),"",L12/(1-M12)) | O12: =IF(OR(N12="",G12=""),"",N12*G12)
E13: =IF(OR(C13="",D13=""),"",D13-C13) | G13: =IF(OR(E13="",F13="",F13=0),"",E13/F13) | K13: =IF(COUNT(H13:J13)=0,"",SUM(H13:J13)) | L13: =IF(OR(G13="",G13=0,K13=""),"",K13/G13) | N13: =IF(OR(L13="",M13="",M13>=1),"",L13/(1-M13)) | O13: =IF(OR(N13="",G13=""),"",N13*G13)
E14: =IF(OR(C14="",D14=""),"",D14-C14) | G14: =IF(OR(E14="",F14="",F14=0),"",E14/F14) | K14: =IF(COUNT(H14:J14)=0,"",SUM(H14:J14)) | L14: =IF(OR(G14="",G14=0,K14=""),"",K14/G14) | N14: =IF(OR(L14="",M14="",M14>=1),"",L14/(1-M14)) | O14: =IF(OR(N14="",G14=""),"",N14*G14)
E15: =IF(OR(C15="",D15=""),"",D15-C15) | G15: =IF(OR(E15="",F15="",F15=0),"",E15/F15) | K15: =IF(COUNT(H15:J15)=0,"",SUM(H15:J15)) | L15: =IF(OR(G15="",G15=0,K15=""),"",K15/G15) | N15: =IF(OR(L15="",M15="",M15>=1),"",L15/(1-M15)) | O15: =IF(OR(N15="",G15=""),"",N15*G15)
E16: =IF(OR(C16="",D16=""),"",D16-C16) | G16: =IF(OR(E16="",F16="",F16=0),"",E16/F16) | K16: =IF(COUNT(H16:J16)=0,"",SUM(H16:J16)) | L16: =IF(OR(G16="",G16=0,K16=""),"",K16/G16) | N16: =IF(OR(L16="",M16="",M16>=1),"",L16/(1-M16)) | O16: =IF(OR(N16="",G16=""),"",N16*G16)
E17: =IF(OR(C17="",D17=""),"",D17-C17) | G17: =IF(OR(E17="",F17="",F17=0),"",E17/F17) | K17: =IF(COUNT(H17:J17)=0,"",SUM(H17:J17)) | L17: =IF(OR(G17="",G17=0,K17=""),"",K17/G17) | N17: =IF(OR(L17="",M17="",M17>=1),"",L17/(1-M17)) | O17: =IF(OR(N17="",G17=""),"",N17*G17)
E18: =IF(OR(C18="",D18=""),"",D18-C18) | G18: =IF(OR(E18="",F18="",F18=0),"",E18/F18) | K18: =IF(COUNT(H18:J18)=0,"",SUM(H18:J18)) | L18: =IF(OR(G18="",G18=0,K18=""),"",K18/G18) | N18: =IF(OR(L18="",M18="",M18>=1),"",L18/(1-M18)) | O18: =IF(OR(N18="",G18=""),"",N18*G18)
E19: =IF(OR(C19="",D19=""),"",D19-C19) | G19: =IF(OR(E19="",F19="",F19=0),"",E19/F19) | K19: =IF(COUNT(H19:J19)=0,"",SUM(H19:J19)) | L19: =IF(OR(G19="",G19=0,K19=""),"",K19/G19) | N19: =IF(OR(L19="",M19="",M19>=1),"",L19/(1-M19)) | O19: =IF(OR(N19="",G19=""),"",N19*G19)
B21: Shaded = you type here. White = calculated for you. Blue numbers are inputs you can change any time (ingredient cost, margin, pan fill).
B23: READING THE JOLLOF EXAMPLE
B24: 330 oz full − 90 oz empty = 240 oz of food. At 7 oz per serving that's about 34 servings. Costs total $58, so each plate costs about $1.70. At a 40% margin you'd charge about $2.85 a serving — roughly $97 for the pan. Change any blue number and every result updates.

Sheet Quote Builder
B2: QUOTE BUILDER
B3: A client tells you how many guests. This works backward to how many pans to make and what to quote.
B5: STEP 1 — Pick a dish from the dropdown (the list comes from YOUR DISHES on the calculator tab)
B6: Dish (pick from dropdown) | C6: Guests to feed | D6: Pans needed | E6: Quote total
B7: EXAMPLES — demo quotes built from the calculator examples
B8: Jollof Chicken & Rice | C8: 60 | D8: =IF(OR(B8="",C8=""),"",IFERROR(ROUNDUP(C8/IFERROR(VLOOKUP(B8,'Pan Pricing Calculator'!$B$7:$O$19,6,FALSE()),""),0),"check dish name")) -> 2 | E8: =IF(OR(D8="",D8="check dish name"),"",IFERROR(D8*IFERROR(VLOOKUP(B8,'Pan Pricing Calculator'!$B$7:$O$19,14,FALSE()),""),"")) -> 193.33333
B9: Beef Lasagna (9×13) | C9: 40 | D9: =IF(OR(B9="",C9=""),"",IFERROR(ROUNDUP(C9/IFERROR(VLOOKUP(B9,'Pan Pricing Calculator'!$B$7:$O$19,6,FALSE()),""),0),"check dish name")) -> 2 | E9: =IF(OR(D9="",D9="check dish name"),"",IFERROR(D9*IFERROR(VLOOKUP(B9,'Pan Pricing Calculator'!$B$7:$O$19,14,FALSE()),""),"")) -> 152.72727
B10: YOUR QUOTES — pick a dish from the dropdown and enter guest count
D11: =IF(OR(B11="",C11=""),"",IFERROR(ROUNDUP(C11/IFERROR(VLOOKUP(B11,'Pan Pricing Calculator'!$B$7:$O$19,6,FALSE()),""),0),"check dish name")) | E11: =IF(OR(D11="",D11="check dish name"),"",IFERROR(D11*IFERROR(VLOOKUP(B11,'Pan Pricing Calculator'!$B$7:$O$19,14,FALSE()),""),""))
D12: =IF(OR(B12="",C12=""),"",IFERROR(ROUNDUP(C12/IFERROR(VLOOKUP(B12,'Pan Pricing Calculator'!$B$7:$O$19,6,FALSE()),""),0),"check dish name")) | E12: =IF(OR(D12="",D12="check dish name"),"",IFERROR(D12*IFERROR(VLOOKUP(B12,'Pan Pricing Calculator'!$B$7:$O$19,14,FALSE()),""),""))
D13: =IF(OR(B13="",C13=""),"",IFERROR(ROUNDUP(C13/IFERROR(VLOOKUP(B13,'Pan Pricing Calculator'!$B$7:$O$19,6,FALSE()),""),0),"check dish name")) | E13: =IF(OR(D13="",D13="check dish name"),"",IFERROR(D13*IFERROR(VLOOKUP(B13,'Pan Pricing Calculator'!$B$7:$O$19,14,FALSE()),""),""))
D14: =IF(OR(B14="",C14=""),"",IFERROR(ROUNDUP(C14/IFERROR(VLOOKUP(B14,'Pan Pricing Calculator'!$B$7:$O$19,6,FALSE()),""),0),"check dish name")) | E14: =IF(OR(D14="",D14="check dish name"),"",IFERROR(D14*IFERROR(VLOOKUP(B14,'Pan Pricing Calculator'!$B$7:$O$19,14,FALSE()),""),""))
D15: =IF(OR(B15="",C15=""),"",IFERROR(ROUNDUP(C15/IFERROR(VLOOKUP(B15,'Pan Pricing Calculator'!$B$7:$O$19,6,FALSE()),""),0),"check dish name")) | E15: =IF(OR(D15="",D15="check dish name"),"",IFERROR(D15*IFERROR(VLOOKUP(B15,'Pan Pricing Calculator'!$B$7:$O$19,14,FALSE()),""),""))
B17: Green numbers pull straight from your calculator. Pans are rounded UP — you can't make half a pan, and a little extra covers big appetites. Adjust up if guests are heavy eaters.
B19: In the YOUR QUOTES rows, click a dish cell and use the dropdown — only dishes you've added under YOUR DISHES on the calculator will appear.
